{
  "name": "handoff",
  "version": "0.0.3",
  "description": "Save task state to disk and resume it in a fresh session by id.",
  "author": { "name": "Krab00" },
  "homepage": "https://github.com/Krab00/junk-drawer",
  "keywords": ["handoff", "continuity", "context"],
  "skills": "./skills/",
  "interface": {
    "displayName": "Handoff",
    "shortDescription": "Save and resume durable task context",
    "longDescription": "Writes durable Markdown handoffs and restores them by short id in another session.",
    "developerName": "Krab00"
  }
}
